pyxeed/__init__.py
pyxeed/seeder.py
pyxeed/xeed.py
pyxeed-0.1.8.dist-info/LICENSE
pyxeed-0.1.8.dist-info/METADATA
pyxeed-0.1.8.dist-info/WHEEL
pyxeed-0.1.8.dist-info/top_level.txt
pyxeed-0.1.8.dist-info/RECORD
