Metadata-Version: 2.1
Name: pyxeed
Version: 0.1.8
Summary: Xeed Core Module Python Version
Home-page: https://github.com/X-I-A/pyxeed
Author: Soral
Author-email: soral@x-i-a.com
License: UNKNOWN
Platform: UNKNOWN
Classifier: Programming Language :: Python :: 3
Classifier: License :: OSI Approved :: GNU Affero General Public License v3 or later (AGPLv3+)
Classifier: Operating System :: OS Independent
Requires-Python: >=3.7
Requires-Dist: xialib
